{
  "resourceType": "StructureDefinition",
  "id": "us-core-race",
  "url": "http://hl7.org/fhir/us/core-r4/StructureDefinition/us-core-race",
  "version": "4.0.0",
  "name": "UsCoreRaceExtension",
  "title": "US Core Race Extension",
  "status": "active",
  "date": "2016-08-01",
  "publisher": "HL7 US Realm Steering Committee",
  "description": "Concepts classifying the person into a named category of humans sharing common history, traits, geographical origin or nationality.  The race codes used to represent these concepts are based upon the [CDC Race and Ethnicity Code Set Version 1.0](http://www.cdc.gov/phin/resources/vocabulary/index.html) which includes over 900 concepts for representing race and ethnicity of which 921 reference race.  The race concepts are grouped by and pre-mapped to the 5 OMB race categories: - American Indian or Alaska Native - Asian - Black or African American - Native Hawaiian or Other Pacific Islander - White.",
  "purpose": "Complies with 2015 Edition Common Clinical Data Set for patient race.",
  "fhirVersion": "4.0.0",
  "mapping": [
    {
      "identity": "rim",
      "uri": "http://hl7.org/v3",
      "name": "RIM Mapping"
    }
  ],
  "kind": "complex-type",
  "abstract": false,
  "context": [
    {
      "type": "element",
      "expression": "Patient"
    }
  ],
  "type": "Extension",
  "baseDefinition": "http://hl7.org/fhir/StructureDefinition/Extension",
  "derivation": "constraint",
  "differential": {
    "element": [
      {
        "id": "Extension:race",
        "path": "Extension",
        "short": "US Core Race Extension",
        "definition": "Concepts classifying the person into a named category of humans sharing common history, traits, geographical origin or nationality.  The race codes used to represent these concepts are based upon the [CDC Race and Ethnicity Code Set Version 1.0](http://www.cdc.gov/phin/resources/vocabulary/index.html) which includes over 900 concepts for representing race and ethnicity of which 921 reference race.  The race concepts are grouped by and pre-mapped to the 5 OMB race categories: - American Indian or Alaska Native - Asian - Black or African American - Native Hawaiian or Other Pacific Islander - White.",
        "min": 0,
        "max": "1",
        "isModifier": false
      },
      {
        "id": "Extension:race.extension:ombcategory",
        "path": "Extension.extension",
        "sliceName": "ombCategory",
        "short": "American Indian or Alaska Native|Asian|Black or African American|Native Hawaiian or Other Pacific Islander|White",
        "definition": "The 5 race category codes according to the [OMB Standards for Maintaining, Collecting, and Presenting Federal Data on Race and Ethnicity, Statistical Policy Directive No. 15, as revised, October 30, 1997](https://www.whitehouse.gov/omb/fedreg_1997standards).",
        "min": 0,
        "max": "5",
        "type": [
          {
            "code": "Extension"
          }
        ],
        "mustSupport": true,
        "isModifier": false,
        "mapping": [
          {
            "identity": "iso11179",
            "map": "/ClinicalDocument/recordTarget/patientRole/patient/raceCode"
          }
        ]
      },
      {
        "id": "Extension:race.extension:ombcategory.url",
        "path": "Extension.extension.url",
        "min": 1,
        "max": "1",
        "type": [
          {
            "code": "uri"
          }
        ],
        "fixedUri": "ombCategory"
      },
      {
        "id": "Extension:race.extension:ombcategory.valueCoding",
        "path": "Extension.extension.valueCoding",
        "min": 1,
        "max": "1",
        "type": [
          {
            "code": "Coding"
          }
        ],
        "binding": {
          "strength": "required",
          "description": "The 5 race category codes according to the [OMB Standards for Maintaining, Collecting, and Presenting Federal Data on Race and Ethnicity, Statistical Policy Directive No. 15, as revised, October 30, 1997](https://www.whitehouse.gov/omb/fedreg_1997standards).",
          "valueSet": "http://hl7.org/fhir/us/core-r4/ValueSet/omb-race-category"
        }
      },
      {
        "id": "Extension:race.extension:detailed",
        "path": "Extension.extension",
        "sliceName": "detailed",
        "short": "Extended race codes",
        "definition": "The 900+ CDC race codes that are grouped under one of the 5 OMB race category codes:.",
        "min": 0,
        "max": "*",
        "type": [
          {
            "code": "Extension"
          }
        ],
        "isModifier": false,
        "mapping": [
          {
            "identity": "iso11179",
            "map": "/ClinicalDocument/recordTarget/patientRole/patient/sdtc:raceCode"
          }
        ]
      },
      {
        "id": "Extension:race.extension:detailed.url",
        "path": "Extension.extension.url",
        "min": 1,
        "max": "1",
        "type": [
          {
            "code": "uri"
          }
        ],
        "fixedUri": "detailed"
      },
      {
        "id": "Extension:race.extension:detailed.valueCoding",
        "path": "Extension.extension.valueCoding",
        "min": 1,
        "max": "1",
        "type": [
          {
            "code": "Coding"
          }
        ],
        "binding": {
          "strength": "required",
          "description": "The [900+ CDC Race codes](http://www.cdc.gov/phin/resources/vocabulary/index.html) that are grouped under one of the 5 OMB race category codes.",
          "valueSet": "http://hl7.org/fhir/us/core-r4/ValueSet/detailed-race"
        }
      },
      {
        "id": "Extension:race.extension:text",
        "path": "Extension.extension",
        "sliceName": "text",
        "short": "Race Text",
        "definition": "Plain text representation of the race concept(s).",
        "min": 1,
        "max": "1",
        "type": [
          {
            "code": "Extension"
          }
        ],
        "mustSupport": true,
        "isModifier": false
      },
      {
        "id": "Extension:race.extension:text.url",
        "path": "Extension.extension.url",
        "min": 1,
        "max": "1",
        "type": [
          {
            "code": "uri"
          }
        ],
        "fixedUri": "text"
      },
      {
        "id": "Extension:race.extension:text.valueString",
        "path": "Extension.extension.valueString",
        "min": 1,
        "max": "1",
        "type": [
          {
            "code": "string"
          }
        ]
      },
      {
        "id": "Extension:race.url",
        "path": "Extension.url",
        "min": 1,
        "max": "1",
        "fixedUri": "http://hl7.org/fhir/us/core-r4/StructureDefinition/us-core-race"
      }
    ]
  }
}
