{
  "resourceType": "StructureDefinition",
  "id": "us-core-goal",
  "url": "http://hl7.org/fhir/us/core-r4/StructureDefinition/us-core-goal",
  "version": "4.0.0",
  "name": "USCoreGoalProfile",
  "title": "US Core Goal Profile",
  "status": "active",
  "date": "2016-08-01",
  "publisher": "HL7 US Realm Steering Committee",
  "description": "Defines constraints and extensions on the Goal resource for the minimal set of data to query and retrieve a patient's goal(s).",
  "fhirVersion": "4.0.0",
  "mapping": [
    {
      "identity": "argonaut-dq-dstu2",
      "uri": "http://unknown.org/Argonaut-DQ-DSTU2",
      "name": "Argonaut-DQ-DSTU2"
    },
    {
      "identity": "v2",
      "uri": "http://hl7.org/v2",
      "name": "HL7 v2 Mapping"
    },
    {
      "identity": "rim",
      "uri": "http://hl7.org/v3",
      "name": "RIM Mapping"
    },
    {
      "identity": "w5",
      "uri": "http://hl7.org/fhir/fivews",
      "name": "FiveWs Pattern Mapping"
    }
  ],
  "kind": "resource",
  "abstract": false,
  "type": "Goal",
  "baseDefinition": "http://hl7.org/fhir/StructureDefinition/Goal",
  "derivation": "constraint",
  "differential": {
    "element": [
      {
        "id": "Goal",
        "path": "Goal",
        "short": "US Core Goal Profile",
        "definition": "The US Core Goal Profile is based upon the core FHIR Goal Resource and created to meet the 2015 Edition Common Clinical Data Set 'Goals' requirements.",
        "mustSupport": false,
        "isModifier": false,
        "mapping": [
          {
            "identity": "argonaut-dq-dstu2",
            "map": "Goal"
          }
        ]
      },
      {
        "id": "Goal.lifecycleStatus",
        "path": "Goal.lifecycleStatus",
        "definition": "Type of plan.",
        "requirements": "Identifies what \"kind\" of plan this is to support differentiation between multiple co-existing plans; e.g. \"Home health\", \"psychiatric\", \"asthma\", \"disease management\", \"wellness plan\", etc.",
        "min": 1,
        "max": "1",
        "type": [
          {
            "code": "code"
          }
        ],
        "mustSupport": true,
        "isModifier": false,
        "binding": {
          "strength": "required",
          "valueSet": "http://hl7.org/fhir/ValueSet/goal-status"
        },
        "mapping": [
          {
            "identity": "argonaut-dq-dstu2",
            "map": "Goal.status"
          }
        ]
      },
      {
        "id": "Goal.description",
        "path": "Goal.description",
        "definition": "proposed | draft | active | completed | cancelled.",
        "requirements": "Indicates whether the plan is currently being acted upon, represents future intentions or is now a historical record.",
        "min": 1,
        "max": "1",
        "type": [
          {
            "code": "CodeableConcept"
          }
        ],
        "mustSupport": true,
        "isModifier": false,
        "mapping": [
          {
            "identity": "argonaut-dq-dstu2",
            "map": "Goal.description"
          }
        ]
      },
      {
        "id": "Goal.subject",
        "path": "Goal.subject",
        "definition": "Who care plan is for.",
        "requirements": "Identifies the patient or group whose intended care is described by the plan.",
        "min": 1,
        "max": "1",
        "type": [
          {
            "code": "Reference",
            "targetProfile": [
              "http://hl7.org/fhir/us/core-r4/StructureDefinition/us-core-patient"
            ]
          }
        ],
        "mustSupport": true,
        "isModifier": false,
        "mapping": [
          {
            "identity": "argonaut-dq-dstu2",
            "map": "Goal.subject"
          }
        ]
      }
    ]
  }
}
